{
  "resolvedId": "/Users/thom/Sites/th-m/th-m.codes.mono/node_modules/solid-start/virtual/entry-client.tsx",
  "transforms": [
    {
      "name": "vite:load-fallback",
      "result": "import { mount, StartClient } from \"../entry-client\";\n\nmount(() => <StartClient />, document);\n",
      "start": 1685056211526,
      "end": 1685056211527
    },
    {
      "name": "solid",
      "result": "import { createComponent as _$createComponent } from \"solid-js/web\";\nimport { mount, StartClient } from \"../entry-client\";\nmount(() => _$createComponent(StartClient, {}), document);",
      "start": 1685056211527,
      "end": 1685056211560,
      "order": "pre"
    }
  ]
}
